[ 0x10] BIPUSH 0x0
[ 0x59] DUP
[ 0x36] ISTORE 0
[ 0x36] ISTORE 1
[ 0x10] BIPUSH 0x20
[ 0xFD] OUT
[ 0x13] LDC_W 0[=0x40]
[ 0xB6] INVOKEVIRTUAL 1[=0x43]
[ 0x36] ISTORE 0
[ 0x10] BIPUSH 0x2B
[ 0xFD] OUT
[ 0x13] LDC_W 0[=0x40]
[ 0xB6] INVOKEVIRTUAL 1[=0x43]
[ 0x36] ISTORE 1
[ 0x10] BIPUSH 0x3D
[ 0x59] DUP
[ 0x59] DUP
[ 0x59] DUP
[ 0x59] DUP
[ 0x59] DUP
[ 0x59] DUP
[ 0x59] DUP
[ 0xFD] OUT
[ 0xFD] OUT
[ 0xFD] OUT
[ 0xFD] OUT
[ 0xFD] OUT
[ 0xFD] OUT
[ 0xFD] OUT
[ 0xFD] OUT
[ 0x10] BIPUSH 0xA
[ 0xFD] OUT
[ 0x15] ILOAD 0
[ 0x15] ILOAD 1
[ 0x60] IADD
[ 0x36] ISTORE 2
[ 0x13] LDC_W 0[=0x40]
[ 0x15] ILOAD 2
[ 0xB6] INVOKEVIRTUAL 2[=0x94]
[ 0xFF] HALT
[  0x0] NOP
[  0x0] NOP
[  0x0] NOP
[  0x1] -
[  0x0] NOP
[  0x1] -
[ 0x10] BIPUSH 0x0
[ 0x36] ISTORE 1
[ 0xFC] IN
[ 0x59] DUP
[ 0x10] BIPUSH 0xA
[ 0x9F] IF_ICMPEQ 0x90
[ 0x59] DUP
[ 0x10] BIPUSH 0x30
[ 0x64] ISUB
[ 0x9B] IFLT 0x8C
[ 0x59] DUP
[ 0x10] BIPUSH 0x3A
[ 0x64] ISUB
[ 0x9B] IFLT 0x77
[ 0x59] DUP
[ 0x10] BIPUSH 0x41
[ 0x64] ISUB
[ 0x9B] IFLT 0x8C
[ 0x59] DUP
[ 0x10] BIPUSH 0x46
[ 0x5F] SWAP
[ 0x64] ISUB
[ 0x9B] IFLT 0x8C
[ 0x59] DUP
[ 0xFD] OUT
[ 0x10] BIPUSH 0x37
[ 0x64] ISUB
[ 0xA7] GOTO 0x7C
[ 0x59] DUP
[ 0xFD] OUT
[ 0x10] BIPUSH 0x30
[ 0x64] ISUB
[ 0x15] ILOAD 1
[ 0x59] DUP
[ 0x60] IADD
[ 0x59] DUP
[ 0x60] IADD
[ 0x59] DUP
[ 0x60] IADD
[ 0x59] DUP
[ 0x60] IADD
[ 0x60] IADD
[ 0x36] ISTORE 1
[ 0xA7] GOTO 0x4B
[ 0x57] POP
[ 0xA7] GOTO 0x4B
[ 0xFD] OUT
[ 0x15] ILOAD 1
[ 0xAC] IRETURN
[  0x0] NOP
[  0x2] -
[  0x0] NOP
[  0x2] -
[ 0x10] BIPUSH 0x9
[ 0x36] ISTORE 3
[ 0x10] BIPUSH 0x1
[ 0x36] ISTORE 2
[ 0x10] BIPUSH 0x0
[ 0x15] ILOAD 3
[ 0x10] BIPUSH 0x1
[ 0x64] ISUB
[ 0x59] DUP
[ 0x99] IFEQ 0xF4
[ 0x36] ISTORE 3
[ 0x15] ILOAD 1
[ 0x15] ILOAD 2
[ 0x7E] IAND
[ 0x99] IFEQ 0xB8
[ 0x10] BIPUSH 0x1
[ 0x60] IADD
[ 0x15] ILOAD 2
[ 0x59] DUP
[ 0x60] IADD
[ 0x36] ISTORE 2
[ 0x15] ILOAD 1
[ 0x15] ILOAD 2
[ 0x7E] IAND
[ 0x99] IFEQ 0xC9
[ 0x10] BIPUSH 0x2
[ 0x60] IADD
[ 0x15] ILOAD 2
[ 0x59] DUP
[ 0x60] IADD
[ 0x36] ISTORE 2
[ 0x15] ILOAD 1
[ 0x15] ILOAD 2
[ 0x7E] IAND
[ 0x99] IFEQ 0xDA
[ 0x10] BIPUSH 0x4
[ 0x60] IADD
[ 0x15] ILOAD 2
[ 0x59] DUP
[ 0x60] IADD
[ 0x36] ISTORE 2
[ 0x15] ILOAD 1
[ 0x15] ILOAD 2
[ 0x7E] IAND
[ 0x99] IFEQ 0xEB
[ 0x10] BIPUSH 0x8
[ 0x60] IADD
[ 0x15] ILOAD 2
[ 0x59] DUP
[ 0x60] IADD
[ 0x36] ISTORE 2
[ 0xA7] GOTO 0xA0
[ 0x57] POP
[ 0x57] POP
[ 0x10] BIPUSH 0x9
[ 0x36] ISTORE 3
[ 0x15] ILOAD 3
[ 0x10] BIPUSH 0x1
[ 0x64] ISUB
[ 0x59] DUP
[ 0x99] IFEQ 0x11A
[ 0x36] ISTORE 3
[ 0x59] DUP
[ 0x10] BIPUSH 0xA
[ 0x64] ISUB
[ 0x9B] IFLT 0x113
[ 0x10] BIPUSH 0x37
[ 0x60] IADD
[ 0xFD] OUT
[ 0xA7] GOTO 0xFA
[ 0x10] BIPUSH 0x30
[ 0x60] IADD
[ 0xFD] OUT
[ 0xA7] GOTO 0xFA
[ 0x10] BIPUSH 0xA
[ 0xFD] OUT
[ 0xAC] IRETURN